m3ushuffler/__init__.py
m3ushuffler/__main__.py
m3ushuffler/m3ushuffler.py
m3ushuffler-0.2.0.dist-info/LICENSE
m3ushuffler-0.2.0.dist-info/METADATA
m3ushuffler-0.2.0.dist-info/WHEEL
m3ushuffler-0.2.0.dist-info/entry_points.txt
m3ushuffler-0.2.0.dist-info/top_level.txt
m3ushuffler-0.2.0.dist-info/RECORD
