Metadata-Version: 2.1
Name: m3ushuffler
Version: 0.2.0
Summary: Shuffle M3U playlists easily
Home-page: https://github.com/Holzhaus/m3ushuffler
Author: Jan Holthuis
Author-email: holthuis.jan@googlemail.com
License: UNKNOWN
Platform: UNKNOWN
Classifier: Programming Language :: Python :: 3
Classifier: License :: OSI Approved :: MIT License
Classifier: Operating System :: OS Independent
